financial_parser/__init__.py
financial_parser/main.py
financial_parser/prompts.py
financial_parser-2025.12.21115104.dist-info/METADATA
financial_parser-2025.12.21115104.dist-info/WHEEL
financial_parser-2025.12.21115104.dist-info/top_level.txt
financial_parser-2025.12.21115104.dist-info/RECORD
