Metadata-Version: 2.4
Name: financial-parser
Version: 2025.12.21115104
Summary: A new package is designed to analyze financial news headlines and extract key structured information such as company names, financial targets, timeframes, and goal updates from text inputs. It simplif
Author-email: financial-parser <hi@eugene.plus>
License: MIT
Project-URL: Homepage, https://github.com/chigwell/financial-parser
Requires-Python: >=3.9
Requires-Dist: langchain-llm7>=0.0.0
Requires-Dist: llmatch-messages>=0.0.0
Requires-Dist: langchain-core>=0.3.0
